demo/annotation/__init__.py
demo/annotation/annotationbody.py
demo/annotation/annotationfixedvocab.py
demo/annotation/annotationlinking.py
demo/annotation/annotationmotivation.py
demo/annotation/annotationrating.py
demo/annotation/annotationtag.py
demo/annotation/annotationtarget.py
demo/annotation/session.py
demo/annotation/toolkit.py
tests/mutations/__init__.py
tests/mutations/test_application.py
tests/mutations/test_audioobject.py
tests/mutations/test_controlaction.py
tests/mutations/test_definedterm.py
tests/mutations/test_digitaldocument.py
tests/mutations/test_entrypoint.py
tests/mutations/test_mediaobject.py
tests/mutations/test_musiccomposition.py
tests/mutations/test_musicgroup.py
tests/mutations/test_musicrecording.py
tests/mutations/test_mutations.py
tests/mutations/test_person.py
tests/mutations/test_place.py
tests/mutations/test_property.py
tests/mutations/test_rating.py
tests/queries/__init__.py
tests/queries/test_mediaobject.py
tests/queries/test_musiccomposition.py
tests/queries/test_person.py
trompace/__init__.py
trompace/config.py
trompace/connection.py
trompace/constants.py
trompace/exceptions.py
trompace/application/__init__.py
trompace/application/application.py
trompace/application/entrypoint_subs.py
trompace/client/__init__.py
trompace/client/client_get_control.py
trompace/client/client_itemlist.py
trompace/client/client_musicplaylist.py
trompace/client/client_send_request.py
trompace/mutations/__init__.py
trompace/mutations/annotation.py
trompace/mutations/application.py
trompace/mutations/audioobject.py
trompace/mutations/controlaction.py
trompace/mutations/definedterm.py
trompace/mutations/digitaldocument.py
trompace/mutations/entrypoint.py
trompace/mutations/itemlist.py
trompace/mutations/mediaobject.py
trompace/mutations/musiccomposition.py
trompace/mutations/musicgroup.py
trompace/mutations/musicplaylist.py
trompace/mutations/musicrecording.py
trompace/mutations/person.py
trompace/mutations/place.py
trompace/mutations/property.py
trompace_client-0.5.dist-info/LICENSE
trompace_client-0.5.dist-info/METADATA
trompace_client-0.5.dist-info/WHEEL
trompace_client-0.5.dist-info/top_level.txt
trompace_client-0.5.dist-info/RECORD
