Metadata-Version: 2.1
Name: trompace-client
Version: 0.5
Summary: A python library to read from and write to the Trompa CE
Home-page: https://github.com/trompamusic/trompa-ce-client
Author: Music Technology Group, Universitat Pompeu Fabra
License: UNKNOWN
Platform: UNKNOWN
Classifier: Development Status :: 4 - Beta
Classifier: Intended Audience :: Developers
Classifier: Programming Language :: Python :: 3
Classifier: License :: OSI Approved :: Apache Software License
Classifier: Operating System :: OS Independent
Classifier: Topic :: Scientific/Engineering :: Information Analysis
Classifier: Topic :: Software Development :: Libraries
Requires-Python: >=3.7
Requires-Dist: requests
Requires-Dist: asyncio
Requires-Dist: aiohttp
Requires-Dist: websockets
Requires-Dist: aiofiles
Requires-Dist: PyJWT (>=2.0.0)
